CHANGES.rst
LICENSE.txt
MANIFEST.in
README.rst
setup.py
examples/demo.py
examples/export.py
examples/soql2atom.py
src/beatbox/__init__.py
src/beatbox/_beatbox.py
src/beatbox/marshall.py
src/beatbox/python_client.py
src/beatbox/xmltramp.py
src/beatboxxx.egg-info/PKG-INFO
src/beatboxxx.egg-info/SOURCES.txt
src/beatboxxx.egg-info/dependency_links.txt
src/beatboxxx.egg-info/not-zip-safe
src/beatboxxx.egg-info/top_level.txt