Metadata-Version: 1.1
Name: beatboxxx
Version: 21.5
Summary: A Python client for the Saleforce.com SOAP API
Home-page: https://github.com/RegioHelden/beatboxxx
Author: RegioHelden GmbH, Simon Fell et al
Author-email: opensource@regiohelden.de
License: GNU GENERAL PUBLIC LICENSE Version 2
Keywords: python salesforce salesforce.com
Platform: UNKNOWN
Classifier: Programming Language :: Python
Classifier: Intended Audience :: Developers
Classifier: Development Status :: 5 - Production/Stable
